LICENSE
MANIFEST.in
README.md
requirements.txt
setup.py
src/BullETS.egg-info/PKG-INFO
src/BullETS.egg-info/SOURCES.txt
src/BullETS.egg-info/dependency_links.txt
src/BullETS.egg-info/requires.txt
src/BullETS.egg-info/top_level.txt
src/bullets/__init__.py
src/bullets/logger.py
src/bullets/runner.py
src/bullets/strategy.py
src/bullets/data_indicators/__init__.py
src/bullets/data_indicators/indicators.py
src/bullets/data_source/__init__.py
src/bullets/data_source/data_source_fmp.py
src/bullets/data_source/data_source_interface.py
src/bullets/data_source/recorded_data.py
src/bullets/portfolio/__init__.py
src/bullets/portfolio/holding.py
src/bullets/portfolio/portfolio.py
src/bullets/portfolio/transaction.py
src/bullets/utils/__init__.py
src/bullets/utils/holiday_date_util.py
src/bullets/utils/market_utils.py
src/test/__init__.py
src/test/test_market.py
src/test/test_portfolio.py
src/test/test_strategy.py
src/test/test_us_holiday.py