Metadata-Version: 2.1
Name: BullETS
Version: 0.1.1
Summary: BullETS is a Python package designed to help with the development of algorithmic trading strategies.
Home-page: https://github.com/AlgoETS/BullETS
Author: AlgoÉTS
License: Apache 2.0
Platform: UNKNOWN
Requires-Python: >=3.7
License-File: LICENSE
